<XnaContent>
<!-- contain enemy 4 Ropes and 2 Stalfos, item Compass, Map, and TriforcePiece, 12 blocks, 3 doors at designed position-->
<Asset Type="MyDataTypes.LevelObjectData[]">
  <Item>
    <ObjectType>Room</ObjectType>
    <ObjectName>Room10</ObjectName>
    <width>192</width>
    <height>112</height>
  </Item>
  <Item>
    <ObjectType>Room</ObjectType>
    <ObjectName>Up</ObjectName>
    <UpRoom>4</UpRoom>
    <UpRoom>4</UpRoom>
  </Item>
  <Item>
    <ObjectType>Room</ObjectType>
    <ObjectName>Down</ObjectName>
    <DownRoom>13</DownRoom>
    <DownRoom>13</DownRoom>
  </Item>
  <Item>
    <ObjectType>Room</ObjectType>
    <ObjectName>Right</ObjectName>
    <RightRoom>6</RightRoom>
    <RightRoom>6</RightRoom>
  </Item>

  <!--  enemy  -->
  <Item>
    <ObjectType>Enemy</ObjectType>
    <ObjectName>Rope</ObjectName>
    <posX>98</posX>
    <posY>84</posY>
  </Item>
  <Item>
    <ObjectType>Enemy</ObjectType>
    <ObjectName>Rope</ObjectName>
    <posX>96</posX>
    <posY>110</posY>
  </Item>
  <Item>
    <ObjectType>Enemy</ObjectType>
    <ObjectName>Rope</ObjectName>
    <posX>64</posX>
    <posY>37</posY>
  </Item>
  <Item>
    <ObjectType>Enemy</ObjectType>
    <ObjectName>Rope</ObjectName>
    <posX>180</posX>
    <posY>90</posY>
  </Item>
  <Item>
    <ObjectType>Enemy</ObjectType>
    <ObjectName>Stalfos</ObjectName>
    <posX>170</posX>
    <posY>55</posY>
  </Item>
  <Item>
    <ObjectType>Enemy</ObjectType>
    <ObjectName>Stalfos</ObjectName>
    <posX>190</posX>
    <posY>110</posY>
  </Item>
  <!--  enemy  -->
  <!--  item  -->
  <Item>
    <ObjectType>Item</ObjectType>
    <ObjectName>Compass</ObjectName>
    <posX>35</posX>
    <posY>80</posY>
  </Item>
  <Item>
    <ObjectType>Item</ObjectType>
    <ObjectName>Map</ObjectName>
    <posX>112</posX>
    <posY>33</posY>
  </Item>
  <Item>
    <ObjectType>Item</ObjectType>
    <ObjectName>TriforcePiece</ObjectName>
    <posX>144</posX>
    <posY>64</posY>
  </Item>
  <!--  item  -->

  <!--  Block  -->
  <Item>
    <ObjectType>Block</ObjectType>
    <ObjectName>Block1</ObjectName>
    <posX>32</posX>
    <posY>32</posY>
  </Item>
  <Item>
    <ObjectType>Block</ObjectType>
    <ObjectName>Block2</ObjectName>
    <posX>32</posX>
    <posY>48</posY>
  </Item>
    <Item>
    <ObjectType>Block</ObjectType>
    <ObjectName>Block3</ObjectName>
    <posX>32</posX>
    <posY>64</posY>
  </Item>
  <Item>
    <ObjectType>Block</ObjectType>
    <ObjectName>Block4</ObjectName>
    <posX>48</posX>
    <posY>32</posY>
  </Item>
  <Item>
    <ObjectType>Block</ObjectType>
    <ObjectName>Block5</ObjectName>
    <posX>48</posX>
    <posY>48</posY>
  </Item>
    <Item>
    <ObjectType>Block</ObjectType>
    <ObjectName>Block6</ObjectName>
    <posX>48</posX>
    <posY>64</posY>
  </Item>
  <Item>
    <ObjectType>Block</ObjectType>
    <ObjectName>Block7</ObjectName>
    <posX>128</posX>
    <posY>32</posY>
  </Item>
    <Item>
    <ObjectType>Block</ObjectType>
    <ObjectName>Block8</ObjectName>
    <posX>128</posX>
    <posY>48</posY>
  </Item>
  <Item>
    <ObjectType>Block</ObjectType>
    <ObjectName>Block9</ObjectName>
    <posX>128</posX>
    <posY>64</posY>
  </Item>
    <Item>
    <ObjectType>Block</ObjectType>
    <ObjectName>Block10</ObjectName>
    <posX>160</posX>
    <posY>32</posY>
  </Item>
    <Item>
    <ObjectType>Block</ObjectType>
    <ObjectName>Block11</ObjectName>
    <posX>160</posX>
    <posY>48</posY>
  </Item>
  <Item>
    <ObjectType>Block</ObjectType>
    <ObjectName>Block12</ObjectName>
    <posX>160</posX>
    <posY>64</posY>
  </Item>
  <!--  Block  -->
  <!--  Door  -->
  <Item>
    <ObjectType>Door</ObjectType>
    <ObjectName>Up</ObjectName>
    <posX>87</posX>
    <posY>0</posY>
  </Item>
  <Item>
    <ObjectType>Door</ObjectType>
    <ObjectName>Down</ObjectName>
    <posX>87</posX>
    <posY>112</posY>
  </Item>
  <Item>
    <ObjectType>Door</ObjectType>
    <ObjectName>Right</ObjectName>
    <posX>192</posX>
    <posY>48</posY>
  </Item>
  <!--  Door  -->
</Asset>
</XnaContent>
